lemongo.py
lemongo-2.0.0b0.dist-info/METADATA
lemongo-2.0.0b0.dist-info/RECORD
lemongo-2.0.0b0.dist-info/WHEEL
lemongo-2.0.0b0.dist-info/entry_points.txt
lemongo-2.0.0b0.dist-info/top_level.txt
