Metadata-Version: 2.1
Name: lemongo
Version: 2.0.0b0
Summary: PyMongo interface for LeBot
Home-page: https://github.com/cganterh/lemongo
Author: Cristóbal Ganter
Author-email: cganterh@gmail.com
License: MIT
Keywords: bot,database,LeBot,MongoDB,PyMongo,Telegram
Platform: UNKNOWN
Classifier: Development Status :: 4 - Beta
Classifier: Environment :: Web Environment
Classifier: Intended Audience :: System Administrators
Classifier: License :: OSI Approved :: MIT License
Classifier: Natural Language :: English
Classifier: Operating System :: POSIX :: Linux
Classifier: Programming Language :: Python :: 3.5
Classifier: Programming Language :: Python :: 3.6
Classifier: Topic :: Communications :: Chat
Classifier: Topic :: Database
Requires-Python: ~=3.5
Requires-Dist: pymongo (~=3.6)
Requires-Dist: python-telegram-bot (~=10.0)
